pqcprep/__init__.py
pqcprep/__main__.py
pqcprep/binary_tools.py
pqcprep/file_tools.py
pqcprep/phase_tools.py
pqcprep/plotting_tools.py
pqcprep/pqc_tools.py
pqcprep/psi_tools.py
pqcprep/resource_tools.py
pqcprep/training_tools.py
pqcprep/resources/amp_state_GR.npy
pqcprep/resources/amp_state_QGAN.npy
pqcprep/resources/full_state_GR.npy
pqcprep/resources/full_state_QGAN.npy
pqcprep/resources/mismatch_QGAN_12.npy
pqcprep/resources/mismatch_QGAN_20.npy
pqcprep/resources/psi_LPF_processed.npy
pqcprep-0.0.1.dist-info/LICENSE.txt
pqcprep-0.0.1.dist-info/METADATA
pqcprep-0.0.1.dist-info/WHEEL
pqcprep-0.0.1.dist-info/entry_points.txt
pqcprep-0.0.1.dist-info/top_level.txt
pqcprep-0.0.1.dist-info/RECORD
