Metadata-Version: 2.1
Name: pqcprep
Version: 0.0.1
Summary: Parametrised quantum circuits for quantum state preparation.
Author-email: David Amorim <2538354a@student.gla.ac.uk>
License: MIT License
Project-URL: Documentation, https://david-f-amorim.github.io/PQC_function_evaluation
Project-URL: GitHub, https://github.com/david-f-amorim/PQC_function_evaluation
Keywords: quantum computing,quantum state preparation,parametrised quantum circuit,quantum machine learning,variational quantum algorithm
Classifier: License :: OSI Approved :: MIT License
Classifier: Programming Language :: Python
Classifier: Programming Language :: Python :: 3
Classifier: Topic :: Scientific/Engineering :: Physics
Classifier: Intended Audience :: Science/Research
Requires-Python: >=3.9
License-File: LICENSE.txt
Requires-Dist: qiskit>=1.1.1
Requires-Dist: numpy
Requires-Dist: matplotlib
Requires-Dist: qiskit-aer>=0.14.2
Requires-Dist: qiskit-machine-learning>=0.7.2
Requires-Dist: torch>=2.0.1
